pygal_maps_china/__init__.py
pygal_maps_china/china.svg
pygal_maps_china/maps.py
pygal_maps_china-1.0.2.dist-info/METADATA
pygal_maps_china-1.0.2.dist-info/WHEEL
pygal_maps_china-1.0.2.dist-info/entry_points.txt
pygal_maps_china-1.0.2.dist-info/top_level.txt
pygal_maps_china-1.0.2.dist-info/RECORD
