Metadata-Version: 2.1
Name: pygal-maps-china
Version: 1.0.2
Summary: pygal maps china
Home-page: UNKNOWN
Author: Gloo
Author-email: gloo.luo@foxmail.com
License: UNKNOWN
Platform: UNKNOWN
